LICENSE
MANIFEST.in
README.md
setup.cfg
setup.py
tap_shippo/__init__.py
tap_shippo.egg-info/PKG-INFO
tap_shippo.egg-info/SOURCES.txt
tap_shippo.egg-info/dependency_links.txt
tap_shippo.egg-info/entry_points.txt
tap_shippo.egg-info/requires.txt
tap_shippo.egg-info/top_level.txt
tap_shippo/schemas/addresses.json
tap_shippo/schemas/parcels.json
tap_shippo/schemas/refunds.json
tap_shippo/schemas/shipments.json
tap_shippo/schemas/transactions.json