Metadata-Version: 1.1
Name: tap-shippo
Version: 0.7.2
Summary: Singer.io tap for extracting data from the Shippo API
Home-page: http://singer.io
Author: Robert J. Moore
Author-email: UNKNOWN
License: UNKNOWN
Platform: UNKNOWN
Classifier: Programming Language :: Python :: 3 :: Only
